dotenv_utils/__about__.py
dotenv_utils/__init__.py
dotenv_utils/casts.py
dotenv_utils-0.2.1.dist-info/METADATA
dotenv_utils-0.2.1.dist-info/WHEEL
dotenv_utils-0.2.1.dist-info/licenses/LICENSE
dotenv_utils-0.2.1.dist-info/RECORD
